tapioca_cloudez/__init__.py
tapioca_cloudez/tapioca_cloudez.py
tapioca_cloudez/resource_mapping/__init__.py
tapioca_cloudez/resource_mapping/addon.py
tapioca_cloudez/resource_mapping/certificate.py
tapioca_cloudez/resource_mapping/cloud_user.py
tapioca_cloudez/resource_mapping/database.py
tapioca_cloudez/resource_mapping/domain.py
tapioca_cloudez/resource_mapping/domain_configuration.py
tapioca_cloudez/resource_mapping/domain_record.py
tapioca_cloudez/resource_mapping/email.py
tapioca_cloudez/resource_mapping/email_account.py
tapioca_cloudez/resource_mapping/email_account_autoreply.py
tapioca_cloudez/resource_mapping/email_group.py
tapioca_cloudez/resource_mapping/migration.py
tapioca_cloudez/resource_mapping/website.py
tapioca_cloudez/resource_mapping/website_cron.py
tapioca_cloudez-1.0.0a14.dist-info/DESCRIPTION.rst
tapioca_cloudez-1.0.0a14.dist-info/METADATA
tapioca_cloudez-1.0.0a14.dist-info/RECORD
tapioca_cloudez-1.0.0a14.dist-info/WHEEL
tapioca_cloudez-1.0.0a14.dist-info/metadata.json
tapioca_cloudez-1.0.0a14.dist-info/top_level.txt
tests/__init__.py
tests/test_tapioca_cloudez.py
