Metadata-Version: 2.0
Name: tapioca-cloudez
Version: 1.0.0a14
Summary: cloudez API wrapper using tapioca
Home-page: https://github.com/humrochagf/tapioca-cloudez
Author: Humberto Rocha
Author-email: humrochagf@gmail.com
License: MIT
Keywords: api,cloud,cloudez,web
Platform: UNKNOWN
Classifier: Development Status :: 3 - Alpha
Classifier: Intended Audience :: Developers
Classifier: License :: OSI Approved :: MIT License
Classifier: Natural Language :: English
Classifier: Programming Language :: Python :: 2
Classifier: Programming Language :: Python :: 2.7
Classifier: Programming Language :: Python :: 3
Classifier: Programming Language :: Python :: 3.1
Classifier: Programming Language :: Python :: 3.2
Classifier: Programming Language :: Python :: 3.3
Classifier: Programming Language :: Python :: 3.4
Classifier: Programming Language :: Python :: 3.5
Classifier: Programming Language :: Python :: 3.6
Requires-Dist: tapioca-wrapper (<2)
